atc_tools/__init__.py
atc_tools/requirements.py
atc_tools/az_databricks_token/AuthLinkOpener.py
atc_tools/az_databricks_token/__init__.py
atc_tools/az_databricks_token/get_ad_access_token.py
atc_tools/az_databricks_token/get_impersonation_authorization_code.py
atc_tools/az_databricks_token/main.py
atc_tools/az_databricks_token/server.py
atc_tools/entry_points/__init__.py
atc_tools/entry_points/task_entry_point_helper.py
atc_tools/format/__init__.py
atc_tools/format/validate_camelcased_cols.py
atc_tools/helpers/ExtractEncodedBody.py
atc_tools/helpers/__init__.py
atc_tools/helpers/get_difference_between_two_dfs.py
atc_tools/helpers/module_helper.py
atc_tools/test_job/RunDetails.py
atc_tools/test_job/__init__.py
atc_tools/test_job/dbcli.py
atc_tools/test_job/dbfs.py
atc_tools/test_job/fetch.py
atc_tools/test_job/main.py
atc_tools/test_job/submit.py
atc_tools/test_job/test_main.py
atc_tools/testing/DataframeTestCase.py
atc_tools/testing/TestHandle.py
atc_tools/testing/__init__.py
atc_tools/time/TimeSequence.py
atc_tools/time/__init__.py
atc_dataplatform_tools-0.1.26.dist-info/LICENSE
atc_dataplatform_tools-0.1.26.dist-info/METADATA
atc_dataplatform_tools-0.1.26.dist-info/WHEEL
atc_dataplatform_tools-0.1.26.dist-info/entry_points.txt
atc_dataplatform_tools-0.1.26.dist-info/top_level.txt
atc_dataplatform_tools-0.1.26.dist-info/RECORD
