Metadata-Version: 2.1
Name: atc-dataplatform-tools
Version: 0.1.26
Summary: A common set of python libraries for DataBricks, supplement to atc-dataplatform
Home-page: https://github.com/atc-net/atc-dataplatform-tools
Author: ATC.Net
Author-email: atcnet.org@gmail.com
License: UNKNOWN
Project-URL: Documentation, https://github.com/atc-net/atc-dataplatform-tools
Project-URL: Bug Reports, https://github.com/atc-net/atc-dataplatform-tools/issues
Project-URL: Source Code, https://github.com/atc-net/atc-dataplatform-tools
Keywords: databricks,pyspark,atc-dataplatform
Platform: UNKNOWN
Classifier: Development Status :: 2 - Pre-Alpha
Classifier: Intended Audience :: Developers
Classifier: Topic :: Software Development :: Build Tools
Classifier: Programming Language :: Python :: 3
Classifier: Programming Language :: Python :: 3.8
Classifier: Programming Language :: Python :: 3 :: Only
Classifier: License :: OSI Approved :: MIT License
Classifier: Operating System :: OS Independent
Requires-Python: >=3.8
Requires-Dist: atc-dataplatform
Requires-Dist: pyyaml (==6.0)
Requires-Dist: importlib-metadata
Requires-Dist: requests
Requires-Dist: dateparser
Requires-Dist: pytest
Provides-Extra: dev
Requires-Dist: check-manifest ; extra == 'dev'
